[
  {"name": "Feca", "img_url": "classe_1.png"},
  {"name": "Osamodas", "img_url": "classe_2.png"},
  {"name": "Enutrof", "img_url": "classe_3.png"},
  {"name": "Sram", "img_url": "classe_4.png"},
  {"name": "Xelor", "img_url": "classe_5.png"},
  {"name": "Ecaflip", "img_url": "classe_6.png"},
  {"name": "Eniripsa", "img_url": "classe_7.png"},
  {"name": "Iop", "img_url": "classe_8.png"},
  {"name": "Cra", "img_url": "classe_9.png"},
  {"name": "Sadida", "img_url": "classe_10.png"},
  {"name": "Sacrieur", "img_url": "classe_11.png"},
  {"name": "Pandawa", "img_url": "classe_12.png"},
  {"name": "Roublard", "img_url": "classe_13.png"},
  {"name": "Zobal", "img_url": "classe_14.png"},
  {"name": "Steamer", "img_url": "classe_15.png"},
  {"name": "Eliotrope", "img_url": "classe_16.png"},
  {"name": "Huppermage", "img_url": "classe_17.png"},
  {"name": "Ouginak", "img_url": "classe_18.png"}
]